pad_final_project/__init__.py
pad_final_project/__main__.py
pad_final_project/streamlit_app.py
pad_final_project/utils.py
pad_final_project-0.1.7.dist-info/METADATA
pad_final_project-0.1.7.dist-info/WHEEL
pad_final_project-0.1.7.dist-info/RECORD
